fmrest/__init__.py
fmrest/cloudserver.py
fmrest/const.py
fmrest/exceptions.py
fmrest/foundset.py
fmrest/record.py
fmrest/server.py
fmrest/utils.py
python_fmrest-1.8.0.dist-info/licenses/LICENSE
python_fmrest-1.8.0.dist-info/METADATA
python_fmrest-1.8.0.dist-info/WHEEL
python_fmrest-1.8.0.dist-info/top_level.txt
python_fmrest-1.8.0.dist-info/RECORD
