Metadata-Version: 2.4
Name: python-fmrest
Version: 1.8.0
Summary: python-fmrest is a wrapper around the FileMaker Data API.
Home-page: https://github.com/davidhamann/python-fmrest
Author: David Hamann
Author-email: dh@davidhamann.de
Classifier: Programming Language :: Python
Classifier: Programming Language :: Python :: 3.6
Classifier: License :: OSI Approved :: MIT License
Classifier: Operating System :: OS Independent
Requires-Python: >=3.6
License-File: LICENSE
Requires-Dist: requests>=2
Provides-Extra: cloud
Requires-Dist: pycognito>=0.1.4; extra == "cloud"
Dynamic: author
Dynamic: author-email
Dynamic: classifier
Dynamic: description
Dynamic: description-content-type
Dynamic: home-page
Dynamic: license-file
Dynamic: provides-extra
Dynamic: requires-dist
Dynamic: requires-python
Dynamic: summary
